[
    {
    "name": "preheadline",
    "label": "Preheadline",
    "required": false,
    "locked": false,
    "validation_regex": "",
    "allow_new_line": false,
    "show_emoji_picker": false,
    "type": "text",
    "placeholder": "",
    "inline_help_text": "",
    "help_text": "",
    "default": null },
    {
        "name": "headline",
        "label": "Headline",
        "required": false,
        "locked": false,
        "validation_regex": "",
        "allow_new_line": false,
        "show_emoji_picker": false,
        "type": "text",
        "default": "Headline"
    }, 
    {
        "name": "subheadline",
        "label": "Subheadline",
        "required": false,
        "locked": false,
        "validation_regex": "",
        "allow_new_line": false,
        "show_emoji_picker": false,
        "type": "text",
        "default": "Subheadline"
    },
    {

        "name": "image",
        "label": "Hero Image",
        "required": false,
        "locked": false,
        "help_text": "",
        "responsive": true,
        "resizable": false,
        "type": "image",
        "default": {
            "src": "https://source.unsplash.com/random",
            "alt": ""
        }
    },
    {
        "name": "btn1_text",
        "label": "Button 1 Text",
        "required": false,
        "locked": false,
        "validation_regex": "",
        "allow_new_line": false,
        "show_emoji_picker": false,
        "type": "text",
        "placeholder": "",
        "inline_help_text": "",
        "help_text": "",
        "default": null 
    },
    {
    "name": "btn1_url",
    "label": "Button 1 Url",
    "required": false,
    "locked": false,
    "validation_regex": "",
    "allow_new_line": false,
    "show_emoji_picker": false,
    "type": "text",
    "placeholder": "",
    "inline_help_text": "",
    "help_text": "",
    "default": null 
    },
    {
        "name": "btn2_text",
        "label": "Button 2 Text",
        "required": false,
        "locked": false,
        "validation_regex": "",
        "allow_new_line": false,
        "show_emoji_picker": false,
        "type": "text",
        "placeholder": "",
        "inline_help_text": "",
        "help_text": "",
        "default": null 
    },
    {
    "name": "btn2_url",
    "label": "Button 2 Url",
    "required": false,
    "locked": false,
    "validation_regex": "",
    "allow_new_line": false,
    "show_emoji_picker": false,
    "type": "text",
    "placeholder": "",
    "inline_help_text": "",
    "help_text": "",
    "default": null 
    }
]