[ {
  "id" : "low_text",
  "name" : "low_text",
  "label" : "Good Description",
  "required" : false,
  "locked" : false,
  "validation_regex" : "",
  "placeholder" : "Description for Good Option",
  "allow_new_line" : false,
  "show_emoji_picker" : false,
  "type" : "text",
  "default" : "Just a little indication. There it is. Look at them little rascals. Follow the lay of the land. It's most important."
}, {
  "id" : "mid_text",
  "name" : "mid_text",
  "label" : "Better Description",
  "required" : false,
  "locked" : false,
  "validation_regex" : "",
  "placeholder" : "Description for Better Option",
  "allow_new_line" : false,
  "show_emoji_picker" : false,
  "type" : "text",
  "default" : "Just a little indication. There it is. Look at them little rascals. Follow the lay of the land. It's most important."
}, {
  "id" : "high_text",
  "name" : "high_text",
  "label" : "Best Description",
  "required" : false,
  "locked" : false,
  "validation_regex" : "",
  "placeholder" : "Description for Best Option",
  "allow_new_line" : false,
  "show_emoji_picker" : false,
  "type" : "text",
  "default" : "Just a little indication. There it is. Look at them little rascals. Follow the lay of the land. It's most important."
}, {
  "id" : "low_cta",
  "name" : "low_cta",
  "label" : "Good CTA",
  "required" : false,
  "locked" : false,
  "type" : "cta"
}, {
  "id" : "mid_cta",
  "name" : "mid_cta",
  "label" : "Better CTA",
  "required" : false,
  "locked" : false,
  "type" : "cta"
}, {
  "id" : "high_cta",
  "name" : "high_cta",
  "label" : "Best CTA",
  "required" : false,
  "locked" : false,
  "type" : "cta"
} ]